fancylog/__init__.py
fancylog/fancylog.py
fancylog/tools/__init__.py
fancylog/tools/git.py
fancylog-0.6.0.dist-info/licenses/LICENSE
fancylog-0.6.0.dist-info/METADATA
fancylog-0.6.0.dist-info/WHEEL
fancylog-0.6.0.dist-info/top_level.txt
fancylog-0.6.0.dist-info/RECORD
