Metadata-Version: 2.4
Name: fancylog
Version: 0.6.0
Summary: Fancier logging in Python
Author-email: Adam Tyson <code@adamltyson.com>
License: BSD-3-Clause
Project-URL: homepage, https://github.com/neuroinformatics-unit/fancylog
Project-URL: bug_tracker, https://github.com/neuroinformatics-unit/fancylog/issues
Project-URL: documentation, https://github.com/neuroinformatics-unit/fancylog
Project-URL: source_code, https://github.com/neuroinformatics-unit/fancylog
Project-URL: user_support, https://github.com/neuroinformatics-unit/fancylog/issues
Classifier: Development Status :: 4 - Beta
Classifier: Programming Language :: Python
Classifier: Programming Language :: Python :: 3
Classifier: Programming Language :: Python :: 3.11
Classifier: Programming Language :: Python :: 3.12
Classifier: Programming Language :: Python :: 3.13
Classifier: Operating System :: OS Independent
Classifier: License :: OSI Approved :: BSD License
Requires-Python: >=3.11
License-File: LICENSE
Requires-Dist: rich
Provides-Extra: dev
Requires-Dist: pytest; extra == "dev"
Requires-Dist: pytest-cov; extra == "dev"
Requires-Dist: coverage; extra == "dev"
Requires-Dist: tox; extra == "dev"
Requires-Dist: pre-commit; extra == "dev"
Requires-Dist: setuptools_scm; extra == "dev"
Provides-Extra: git
Requires-Dist: gitpython; extra == "git"
Provides-Extra: multiprocessing
Requires-Dist: multiprocessing-logging; extra == "multiprocessing"
Dynamic: license-file
